aclc_ba/VERSION
aclc_ba/__init__.py
aclc_ba/morphology/__init__.py
aclc_ba/morphology/analysis.py
aclc_ba/morphology/bw_solutions.py
aclc_ba/morphology/db_analyzer_based.py
aclc_ba/morphology/word_solution.py
aclc_ba/morphology/disambiguator/__init__.py
aclc_ba/morphology/disambiguator/disambig.py
aclc_ba/tests/README.rst
aclc_ba/tests/__init__.py
aclc_ba/tests/test_data_reader.py
aclc_ba/tests/morphology/test_analysis.py
aclc_ba/tests/morphology/test_bw_solutions.py
aclc_ba/tests/morphology/test_db_analyzed_based.py
aclc_ba/tests/tokenizer/__init__.py
aclc_ba/tests/tokenizer/test_sentence_markup.py
aclc_ba/tests/tokenizer/test_tokenize.py
aclc_ba/tokenizer/__init__.py
aclc_ba/tokenizer/post_tokenize.py
aclc_ba/tokenizer/sentence_markup.py
aclc_ba/tokenizer/tokenize.py
aclc_ba/utils/__init__.py
aclc_ba/utils/data_reader.py
aclc_ba/utils/dis_tag_lemma_logprop.csv
aclc_ba/utils/edited_word_count.csv
aclc_ba/utils/segmentation_matching.py
aclc_ba/utils/translitration.py
aclc_ba/utils/Buckwalter/data/AraMorph.pl
aclc_ba/utils/Buckwalter/data/bw_solutions_out.csv
aclc_ba/utils/Buckwalter/data/dictPrefixes
aclc_ba/utils/Buckwalter/data/dictStems
aclc_ba/utils/Buckwalter/data/dictSuffixes
aclc_ba/utils/Buckwalter/data/in.txt
aclc_ba/utils/Buckwalter/data/tableAB
aclc_ba/utils/Buckwalter/data/tableAC
aclc_ba/utils/Buckwalter/data/tableBC
aclc_ba/utils/Buckwalter/doc/file.tbl
aclc_ba/utils/Buckwalter/doc/license.txt
aclc_ba/utils/Buckwalter/doc/readme.txt
aclc_ba-0.0a1.dev1.dist-info/LICENSE
aclc_ba-0.0a1.dev1.dist-info/METADATA
aclc_ba-0.0a1.dev1.dist-info/WHEEL
aclc_ba-0.0a1.dev1.dist-info/dependency_links.txt
aclc_ba-0.0a1.dev1.dist-info/top_level.txt
aclc_ba-0.0a1.dev1.dist-info/RECORD
